Workbook

Sheet README
A1: Table of Contents: - MASTER_Monthly Tab: The raw dataset to be transformed and warehoused, ready to turn into insightful reports. - REPORT_Pack Tab: A sample report that would come out of a cleaned dataset, after the necessary data wrangling processes. This can also be done using business tools, such as Power BI or Looker Studio. For the purposes of highlighting the entire reporting process, I have consolidated everything in this file, including the report, instead of a BI tool. - DQ_Checks Tab: A visual preview of a raw dataset undergoing ETL and data wrangling processes, with included quality and accuracy checks. - SQL_Bonus Tab: A simple preview of raw SQL (Power Query) skills, if needed.
A16: Assumptions: - Chose all available data ranges (aug 2024 - aug 2025) for maximum reporting potential (YoYs, YtY, YtM). - Pullled all relevant and available data, but only pulled the parent datasets from the Ashwagandha and K2D3 entities. - Identified "calculated fields" aka derivable values for data quality inspection. These cases have their columns color filled in light gray 1. | C16: Judgement Calls: - Converted "stubborn" variables into their proper datatypes for uniformity, with percentages having the most prominent cases. For example : 23.1 != 23.1% in Google Sheets standards, because 23.1% == 0.231. These cases are highlighted in bold, dark blue 3 text color. Other cases include the conversion of "AOV" values into a monetary datatype, and the restoration of values with wrong datatypes to their correct ones. For example: "Units Sold" is not a money datatype, but one that concerns supply. I simply removed the dollar signs.
A18: Data Quality Remarks: - Issue: outright missing data. the Ashwagandha and K2D3 entities do not have the following metrics: AOV, Units Sold, Avg Units Order, UnitSes%. Solution used: Data Imputation via standard derivation formulas (shown in the DQ_Checks tab). These cases are highlighted in bold, light red berry 1 text color. - Data Verification: standard check if the raw values are equivalent to its calculated/derived value, and to indentify mismatches. These cases have their column headers color filled in dark orange 15. | C18: Data Insights: - 2025 has shown improvements as compared to its previous year. The overall conversion rates have been steadily increasing throughout the months, which shows a sign of increased traffic. - July 2025 in particular has proved to be the best month, having the highest revenue, order count, sold units, and repeat share all coincide in this month.

Sheet MASTER_Monthly
D1: Assumptions: - Chose all available data ranges (aug 2024 - aug 2025) for maximum reporting potential (YoYs, YtY, YtM). - Pullled all relevant and available data, but only pulled the parent datasets from the Ashwagandha and K2D3 entities. - Identified "calculated fields" aka derivable values for data quality inspection. These cases have their columns color filled in light gray 1.
A10: Month | B10: Entity | C10: Total Sales | D10: Profit From Sales | E10: Profit Margin | F10: Overall CVR | G10: PPC CVR | H10: Organic CVR | I10: Total Sessions | J10: PPC Sessions (PPC Clicks) | K10: Organic Traffic | L10: Total Orders | M10: PPC Orders | N10: Organic Orders | O10: Avg Order Value | P10: Units Sold | Q10: Avg Units Order | R10: UnitSes% | S10: New to Brand Sales | T10: Repeated sales | U10: %new to brand | V10: %repeat
A11: 45505 | B11: Account | C11: 921287 | D11: 212777 | E11: 0.231 | F11: 0.188 | G11: 0.3416 | H11: 0.1724 | I11: 206628 | J11: 19109 | K11: 187519 | L11: 38847 | M11: 6527 | N11: 32320 | O11: 23.72 | P11: 44419 | Q11: 1.14 | R11: 0.215 | S11: 493881 | T11: 427406 | U11: 0.53607725 | V11: 0.46392275
A12: 45505 | B12: Ashwagandha | C12: 157936 | D12: 34841 | E12: 0.2206 | F12: 0.1951 | G12: 0.3302 | H12: 0.168 | I12: 42573 | J12: 7101 | K12: 35472 | L12: 8304 | M12: 2345 | N12: 5959 | O12: 19.019268 | P12: 8304 | Q12: 1 | R12: 0.1951 | S12: 78543 | T12: 79393 | U12: 0.49730904 | V12: 0.50269096
A13: 45505 | B13: K2D3 | C13: 73428 | D13: 14579 | E13: 0.1986 | F13: 0.3058 | G13: 0.378 | H13: 0.2777 | I13: 11469 | J13: 3206 | K13: 8263 | L13: 3507 | M13: 1212 | N13: 2295 | O13: 20.937553 | P13: 3507 | Q13: 1 | R13: 0.3058 | S13: 34682 | T13: 38746 | U13: 0.47232663 | V13: 0.52767337
A14: 45536 | B14: Account | C14: 948029 | D14: 197946 | E14: 0.2088 | F14: 0.2007 | G14: 0.3255 | H14: 0.1865 | I14: 201584 | J14: 20522 | K14: 181062 | L14: 40450 | M14: 6680 | N14: 33770 | O14: 23.44 | P14: 45915 | Q14: 1.14 | R14: 0.2278 | S14: 500394 | T14: 447635 | U14: 0.52782563 | V14: 0.47217437
A15: 45536 | B15: Ashwagandha | C15: 153828 | D15: 30441 | E15: 0.1979 | F15: 0.2091 | G15: 0.3376 | H15: 0.177 | I15: 38401 | J15: 7658 | K15: 30743 | L15: 8028 | M15: 2585 | N15: 5443 | O15: 19.161435 | P15: 8028 | Q15: 1 | R15: 0.2091 | S15: 74109 | T15: 79719 | U15: 0.48176535 | V15: 0.51823465
A16: 45536 | B16: K2D3 | C16: 94601 | D16: 18329 | E16: 0.1937 | F16: 0.3125 | G16: 0.3496 | H16: 0.3099 | I16: 15356 | J16: 1024 | K16: 14332 | L16: 4799 | M16: 358 | N16: 4441 | O16: 19.712648 | P16: 4799 | Q16: 1 | R16: 0.3125 | S16: 47718 | T16: 46883 | U16: 0.50441327 | V16: 0.49558673
A17: 45566 | B17: Account | C17: 993750 | D17: 183147 | E17: 0.1843 | F17: 0.2008 | G17: 0.3086 | H17: 0.1825 | I17: 209554 | J17: 30381 | K17: 179173 | L17: 42077 | M17: 9377 | N17: 32700 | O17: 23.62 | P17: 48549 | Q17: 1.15 | R17: 0.2317 | S17: 486763 | T17: 506987 | U17: 0.4898244 | V17: 0.5101756
A18: 45566 | B18: Ashwagandha | C18: 162480 | D18: 28164 | E18: 0.1733 | F18: 0.2192 | G18: 0.3171 | H18: 0.1938 | I18: 38675 | J18: 7967 | K18: 30708 | L18: 8478 | M18: 2526 | N18: 5952 | O18: 19.164897 | P18: 8478 | Q18: 1 | R18: 0.2192 | S18: 72430 | T18: 90050 | U18: 0.44577794 | V18: 0.55422206
A19: 45566 | B19: K2D3 | C19: 117918 | D19: 19809 | E19: 0.168 | F19: 0.2828 | G19: 0.3344 | H19: 0.2671 | I19: 20833 | J19: 4844 | K19: 15989 | L19: 5891 | M19: 1620 | N19: 4271 | O19: 20.016636 | P19: 5891 | Q19: 1 | R19: 0.2828 | S19: 58393 | T19: 59525 | U19: 0.49520005 | V19: 0.50479995
A20: 45597 | B20: Account | C20: 1022469 | D20: 170017 | E20: 0.1663 | F20: 0.1847 | G20: 0.3127 | H20: 0.1699 | I20: 235393 | J20: 24397 | K20: 210996 | L20: 43480 | M20: 7628 | N20: 35852 | O20: 23.52 | P20: 50265 | Q20: 1.16 | R20: 0.2135 | S20: 501876 | T20: 520593 | U20: 0.49084716 | V20: 0.50915284
A21: 45597 | B21: Ashwagandha | C21: 158885 | D21: 26311 | E21: 0.1656 | F21: 0.2185 | G21: 0.3344 | H21: 0.1978 | I21: 38659 | J21: 5858 | K21: 32801 | L21: 8448 | M21: 1959 | N21: 6489 | O21: 18.80741 | P21: 8448 | Q21: 1 | R21: 0.2185 | S21: 69552 | T21: 89333 | U21: 0.43775057 | V21: 0.56224943
A22: 45597 | B22: K2D3 | C22: 114352 | D22: 19650 | E22: 0.1718 | F22: 0.2316 | G22: 0.3176 | H22: 0.2037 | I22: 23353 | J22: 5721 | K22: 17632 | L22: 5408 | M22: 1817 | N22: 3591 | O22: 21.14497 | P22: 5408 | Q22: 1 | R22: 0.2316 | S22: 59120 | T22: 55232 | U22: 0.51700014 | V22: 0.48299986
... A49: 45870 | B49: K2D3 | C49: 115497 | D49: 23860 | E49: 0.2066 | F49: 0.3748 | G49: 0.3494 | H49: 0.3896 | I49: 14604 | J49: 5406 | K49: 9198 | L49: 5473 | M49: 1889 | N49: 3584 | O49: 21.103051 | P49: 5473 | Q49: 1 | R49: 0.3748 | S49: 42524 | T49: 72973 | U49: 0.36818272 | V49: 0.63181728

Sheet REPORT_Pack
A1: Section 1 & 2 - Account Summary and Product Lines | C1: Timeline | D1: Entity
C2: 45839 | D2: Account | I2: Data Insights: - 2025 has shown improvements as compared to its previous year. The overall conversion rates have been steadily increasing throughout the months, which shows a sign of increased traffic. - July 2025 in particular has proved to be the best month, having the highest revenue, order count, sold units, and repeat share all coincide in this month.
A4: Total Sales | B4: Profit | C4: Profit Margin | D4: Orders | E4: Sessions | F4: CVR | G4: AOV
A5: =SUMIFS(MASTER_Monthly!C11:C1000, MASTER_Monthly!B11:B1000, "="&D2, MASTER_Monthly!A11:A1000, "="&C2) -> 1420531 | B5: =SUMIFS(MASTER_Monthly!D11:D1000, MASTER_Monthly!B11:B1000, "="&D2, MASTER_Monthly!A11:A1000, "="&C2) -> 334195 | C5: =AVERAGEIFS(MASTER_Monthly!E11:E1000, MASTER_Monthly!B11:B1000, "="&D2, MASTER_Monthly!A11:A1000, "="&C2) -> 0.2353 | D5: =SUMIFS(MASTER_Monthly!L11:L1000, MASTER_Monthly!B11:B1000, "="&D2, MASTER_Monthly!A11:A1000, "="&C2) -> 57185 | E5: =SUMIFS(MASTER_Monthly!I11:I1000, MASTER_Monthly!B11:B1000, "="&D2, MASTER_Monthly!A11:A1000, "="&C2) -> 244791 | F5: =AVERAGEIFS(MASTER_Monthly!F11:F1000, MASTER_Monthly!B11:B1000, "="&D2, MASTER_Monthly!A11:A1000, "="&C2) -> 0.2336 | G5: =AVERAGEIFS(MASTER_Monthly!O11:O1000, MASTER_Monthly!B11:B1000, "="&D2, MASTER_Monthly!A11:A1000, "="&C2) -> 24.84
A7: vs Prev. Month | B7: vs Prev. Month | C7: vs Prev. Month | D7: vs Prev. Month | E7: vs Prev. Month | F7: vs Prev. Month | G7: vs Prev. Month
A8: =(A5 - (SUMIFS(MASTER_Monthly!C11:C1000, MASTER_Monthly!B11:B1000, "="&D2, MASTER_Monthly!A11:A1000, "="&DATE(YEAR(C2), (MONTH(C2) - 1), 1) ))) / (SUMIFS(MASTER_Monthly!C11:C1000, MASTER_Monthly!B11:B1000, "="&D2, MASTER_Monthly!A11:A1000, "="&DATE(YEAR(C2), (MONTH(C2) - 1), 1) )) -> 0.23182309 | B8: =(B5 - (SUMIFS(MASTER_Monthly!D11:D1000, MASTER_Monthly!B11:B1000, "="&D2, MASTER_Monthly!A11:A1000, "="&DATE(YEAR(C2), (MONTH(C2) - 1), 1) ))) / (SUMIFS(MASTER_Monthly!D11:D1000, MASTER_Monthly!B11:B1000, "="&D2, MASTER_Monthly!A11:A1000, "="&DATE(YEAR(C2), (MONTH(C2) - 1), 1) )) -> 0.16418696 | C8: =(C5 - (AVERAGEIFS(MASTER_Monthly!E11:E1000, MASTER_Monthly!B11:B1000, "="&D2, MASTER_Monthly!A11:A1000, "="&DATE(YEAR(C2), (MONTH(C2) - 1), 1) ))) / (AVERAGEIFS(MASTER_Monthly!E11:E1000, MASTER_Monthly!B11:B1000, "="&D2, MASTER_Monthly!A11:A1000, "="&DATE(YEAR(C2), (MONTH(C2) - 1), 1) )) -> -0.054640418 | D8: =(D5 - (SUMIFS(MASTER_Monthly!L11:L1000, MASTER_Monthly!B11:B1000, "="&D2, MASTER_Monthly!A11:A1000, "="&DATE(YEAR(C2), (MONTH(C2) - 1), 1) ))) / (SUMIFS(MASTER_Monthly!L11:L1000, MASTER_Monthly!B11:B1000, "="&D2, MASTER_Monthly!A11:A1000, "="&DATE(YEAR(C2), (MONTH(C2) - 1), 1) )) -> 0.29800708 | E8: =(E5 - (SUMIFS(MASTER_Monthly!I11:I1000, MASTER_Monthly!B11:B1000, "="&D2, MASTER_Monthly!A11:A1000, "="&DATE(YEAR(C2), (MONTH(C2) - 1), 1) ))) / (SUMIFS(MASTER_Monthly!I11:I1000, MASTER_Monthly!B11:B1000, "="&D2, MASTER_Monthly!A11:A1000, "="&DATE(YEAR(C2), (MONTH(C2) - 1), 1) )) -> 0.2251066 | F8: =(F5 - (AVERAGEIFS(MASTER_Monthly!F11:F1000, MASTER_Monthly!B11:B1000, "="&D2, MASTER_Monthly!A11:A1000, "="&DATE(YEAR(C2), (MONTH(C2) - 1), 1) ))) / (AVERAGEIFS(MASTER_Monthly!F11:F1000, MASTER_Monthly!B11:B1000, "="&D2, MASTER_Monthly!A11:A1000, "="&DATE(YEAR(C2), (MONTH(C2) - 1), 1) )) -> 0.059410431 | G8: =(G5 - (AVERAGEIFS(MASTER_Monthly!O11:O1000, MASTER_Monthly!B11:B1000, "="&D2, MASTER_Monthly!A11:A1000, "="&DATE(YEAR(C2), (MONTH(C2) - 1), 1) ))) / (AVERAGEIFS(MASTER_Monthly!O11:O1000, MASTER_Monthly!B11:B1000, "="&D2, MASTER_Monthly!A11:A1000, "="&DATE(YEAR(C2), (MONTH(C2) - 1), 1) )) -> -0.05118411

Sheet DQ_Checks
D1: Data Quality Remarks: - Issue: outright missing data. the Ashwagandha and K2D3 entities do not have the following metrics: AOV, Units Sold, Avg Units Order, UnitSes%. Solution used: Data Imputation via standard derivation formulas (shown in the DQ_Checks tab). These cases are highlighted in bold, light red berry 1 text color. - Data Verification: standard check if the raw values are equivalent to its calculated/derived value, and to indentify mismatches. These cases have their column headers color filled in dark orange 15.
C9: Grand Total | D9: Grand Total | F9: Grand Total | G9: Grand Total | H9: Grand Total | I9: Grand Total | J9: Grand Total | K9: Grand Total | L9: Grand Total | M9: Grand Total | N9: Grand Total | O9: Grand Total | R9: Grand Total | S9: Grand Total | V9: Grand Total | W9: Grand Total | X9: Grand Total | Y9: Grand Total | Z9: Grand Total | AA9: Grand Total | AB9: Grand Total | AC9: Grand Total | AF9: Grand Total | AG9: Grand Total | AH9: Grand Total | AI9: Grand Total
C10: =SUM(C15:C54) -> 18412413 | D10: =SUM(D15:D54) -> 18409085 | F10: =SUM(F15:F54) -> 8.5965 | G10: =SUM(G15:G54) -> 8.5965 | H10: =SUM(H15:H54) -> 9.2638 | I10: =SUM(I15:I54) -> 9.2638 | J10: =SUM(J15:J54) -> 12.4546 | K10: =SUM(K15:K54) -> 12.4546 | L10: =SUM(L15:L54) -> 8.3479 | M10: =SUM(M15:M54) -> 8.3479 | ... O10: =SUM(O15:O54) -> 3763919 | R10: =SUM(R15:R54) -> 775646 | S10: =SUM(S15:S54) -> 775646 | V10: =SUM(V15:V54) -> 858.41233 | W10: =SUM(W15:W54) -> 858.40557 | X10: =SUM(X15:X54) -> 859630 | Y10: =SUM(Y15:Y54) -> 775635.23 | Z10: =SUM(Z15:Z54) -> 40.84 | AA10: =SUM(AA15:AA54) -> 40.84 | AB10: =SUM(AB15:AB54) -> 9.6266 | AC10: =SUM(AC15:AC54) -> 9.6266 | AF10: =SUM(AF15:AF54) -> 17.864607 | AG10: =SUM(AG15:AG54) -> 17.8636 | AH10: =SUM(AH15:AH54) -> 21.135393 | AI10: =SUM(AI15:AI54) -> 21.134
D11: Difference | G11: Difference | I11: Difference | K11: Difference | M11: Difference | O11: Difference | S11: Difference | W11: Difference | Y11: Difference | AA11: Difference | AC11: Difference | AG11: Difference | AI11: Difference
D12: =C10 -D10 -> 3328 | G12: =F10 -G10 -> 0 | I12: =H10 -I10 -> 0 | K12: =J10 -K10 -> 0 | M12: =L10 -M10 -> 0 | O12: =N10 -O10 -> 0 | S12: =R10 -S10 -> 0 | W12: =V10 - W10 -> 0.0067608438 | Y12: =X10 - Y10 -> 83994.765 | AA12: =Z10 -AA10 -> 0 | AC12: =AB10 -AC10 -> 0 | AG12: =AF10 -AG10 -> 0.0010067405 | AI12: =AH10 -AI10 -> 0.0013932595
D14: Formula: new to brand sales + repeated sales | G14: Formula: Profit From Sales / Total Sales | I14: Formula: Total Orders / Total Sessions | K14: Formula: PPC Orders / PPC Sessions | M14: Formula: Organic Orders / Organic Traffic | O14: Formula: PPC Sessions + Organic Traffic | S14: Formula: PPC Orders + Organic Orders | W14: Formula: Total Sales / Total Orders | Y14: Formula: Total Sales/ Avg Order Value | AA14: Formula: Units Sold / Total Orders | AC14: Formula: Units Sold / Total Sessions | AG14: Formula: New to Brand Sales / Total Sales | AI14: Formula: Repeat Sales / Total Sales
A15: Month | B15: Entity | C15: Total Sales | D15: TOTAL SALES, DQ | E15: Profit From Sales | F15: Profit Margin | G15: PROFIT MARGIN, DQ | H15: Overall CVR | I15: OVERALL CVR, DQ | J15: PPC CVR | K15: PPC CVR, DQ | L15: Organic CVR | M15: ORGANIC CVR, DQ | N15: Total Sessions | O15: TOTAL SESSIONS, DQ | P15: PPC Sessions (PPC Clicks) | Q15: Organic Traffic | R15: Total Orders | S15: TOTAL ORDERS, DQ | T15: PPC Orders | U15: Organic Orders | V15: Avg Order Value | W15: AVG ORDER VALUE, DQ | X15: Units Sold | Y15: UNITS SOLD, DQ | Z15: Avg Units Order | AA15: AVG UNITS ORDER, DQ | AB15: UnitSes% | AC15: UNITSES%, DQ | AD15: New to Brand Sales | AE15: Repeated sales | AF15: %new to brand | AG15: %NEW TO BRAND, DQ | AH15: %repeat | AI15: %REPEAT, DQ
A16: 45505 | B16: Account | C16: 921287 | D16: =AD16 + AE16 -> 921287 | E16: 212777 | F16: 0.231 | G16: =ROUND(E16/C16, 4) -> 0.231 | H16: 0.188 | I16: =ROUND(R16/N16, 4) -> 0.188 | J16: 0.3416 | K16: =ROUND(T16/P16, 4) -> 0.3416 | L16: 0.1724 | M16: =ROUND(U16/Q16, 4) -> 0.1724 | N16: 206628 | O16: =P16 + Q16 -> 206628 | P16: 19109 | Q16: 187519 | R16: 38847 | S16: =T16 + U16 -> 38847 | T16: 6527 | U16: 32320 | V16: 23.72 | W16: =C16 / R16 -> 23.715782 | X16: 44419 | Y16: =C16 / V16 -> 38840.093 | Z16: 1.14 | AA16: =ROUND(X16/R16, 2) -> 1.14 | AB16: 0.215 | AC16: =ROUND(X16 / N16, 4) -> 0.215 | AD16: 493881 | AE16: 427406 | AF16: 0.53607725 | AG16: =ROUND(AD16 / C16, 4) -> 0.5361 | AH16: 0.46392275 | AI16: =ROUND(AE16 / C16, 4) -> 0.4639
A17: 45536 | B17: Account | C17: 948029 | D17: =AD17 + AE17 -> 948029 | E17: 197946 | F17: 0.2088 | G17: =ROUND(E17/C17, 4) -> 0.2088 | H17: 0.2007 | I17: =ROUND(R17/N17, 4) -> 0.2007 | J17: 0.3255 | K17: =ROUND(T17/P17, 4) -> 0.3255 | L17: 0.1865 | M17: =ROUND(U17/Q17, 4) -> 0.1865 | N17: 201584 | O17: =P17 + Q17 -> 201584 | P17: 20522 | Q17: 181062 | R17: 40450 | S17: =T17 + U17 -> 40450 | T17: 6680 | U17: 33770 | V17: 23.44 | W17: =C17 / R17 -> 23.437058 | X17: 45915 | Y17: =C17 / V17 -> 40444.923 | Z17: 1.14 | AA17: =ROUND(X17/R17, 2) -> 1.14 | AB17: 0.2278 | AC17: =ROUND(X17 / N17, 4) -> 0.2278 | AD17: 500394 | AE17: 447635 | AF17: 0.52782563 | AG17: =ROUND(AD17 / C17, 4) -> 0.5278 | AH17: 0.47217437 | AI17: =ROUND(AE17 / C17, 4) -> 0.4722
A18: 45566 | B18: Account | C18: 993750 | D18: =AD18 + AE18 -> 993750 | E18: 183147 | F18: 0.1843 | G18: =ROUND(E18/C18, 4) -> 0.1843 | H18: 0.2008 | I18: =ROUND(R18/N18, 4) -> 0.2008 | J18: 0.3086 | K18: =ROUND(T18/P18, 4) -> 0.3086 | L18: 0.1825 | M18: =ROUND(U18/Q18, 4) -> 0.1825 | N18: 209554 | O18: =P18 + Q18 -> 209554 | P18: 30381 | Q18: 179173 | R18: 42077 | S18: =T18 + U18 -> 42077 | T18: 9377 | U18: 32700 | V18: 23.62 | W18: =C18 / R18 -> 23.617416 | X18: 48549 | Y18: =C18 / V18 -> 42072.396 | Z18: 1.15 | AA18: =ROUND(X18/R18, 2) -> 1.15 | AB18: 0.2317 | AC18: =ROUND(X18 / N18, 4) -> 0.2317 | AD18: 486763 | AE18: 506987 | AF18: 0.4898244 | AG18: =ROUND(AD18 / C18, 4) -> 0.4898 | AH18: 0.5101756 | AI18: =ROUND(AE18 / C18, 4) -> 0.5102
A19: 45597 | B19: Account | C19: 1022469 | D19: =AD19 + AE19 -> 1022469 | E19: 170017 | F19: 0.1663 | G19: =ROUND(E19/C19, 4) -> 0.1663 | H19: 0.1847 | I19: =ROUND(R19/N19, 4) -> 0.1847 | J19: 0.3127 | K19: =ROUND(T19/P19, 4) -> 0.3127 | L19: 0.1699 | M19: =ROUND(U19/Q19, 4) -> 0.1699 | N19: 235393 | O19: =P19 + Q19 -> 235393 | P19: 24397 | Q19: 210996 | R19: 43480 | S19: =T19 + U19 -> 43480 | T19: 7628 | U19: 35852 | V19: 23.52 | W19: =C19 / R19 -> 23.515846 | X19: 50265 | Y19: =C19 / V19 -> 43472.321 | Z19: 1.16 | AA19: =ROUND(X19/R19, 2) -> 1.16 | AB19: 0.2135 | AC19: =ROUND(X19 / N19, 4) -> 0.2135 | AD19: 501876 | AE19: 520593 | AF19: 0.49084716 | AG19: =ROUND(AD19 / C19, 4) -> 0.4908 | AH19: 0.50915284 | AI19: =ROUND(AE19 / C19, 4) -> 0.5092
A20: 45627 | B20: Account | C20: 961094 | D20: =AD20 + AE20 -> 961094 | E20: 224070 | F20: 0.2331 | G20: =ROUND(E20/C20, 4) -> 0.2331 | H20: 0.1764 | I20: =ROUND(R20/N20, 4) -> 0.1764 | J20: 0.3064 | K20: =ROUND(T20/P20, 4) -> 0.3064 | L20: 0.1527 | M20: =ROUND(U20/Q20, 4) -> 0.1527 | N20: 222858 | O20: =P20 + Q20 -> 222858 | P20: 34476 | Q20: 188382 | R20: 39320 | S20: =T20 + U20 -> 39320 | T20: 10562 | U20: 28758 | V20: 24.44 | W20: =C20 / R20 -> 24.442879 | X20: 44946 | Y20: =C20 / V20 -> 39324.632 | Z20: 1.14 | AA20: =ROUND(X20/R20, 2) -> 1.14 | AB20: 0.2017 | AC20: =ROUND(X20 / N20, 4) -> 0.2017 | AD20: 478056 | AE20: 483038 | AF20: 0.49740816 | AG20: =ROUND(AD20 / C20, 4) -> 0.4974 | AH20: 0.50259184 | AI20: =ROUND(AE20 / C20, 4) -> 0.5026
A21: 45658 | B21: Account | C21: 1255515 | D21: =AD21 + AE21 -> 1255515 | E21: 311215 | F21: 0.2479 | G21: =ROUND(E21/C21, 4) -> 0.2479 | H21: 0.1712 | I21: =ROUND(R21/N21, 4) -> 0.1712 | J21: 0.2921 | K21: =ROUND(T21/P21, 4) -> 0.2921 | L21: 0.1398 | M21: =ROUND(U21/Q21, 4) -> 0.1398 | N21: 292426 | O21: =P21 + Q21 -> 292426 | P21: 60260 | Q21: 232166 | R21: 50063 | S21: =T21 + U21 -> 50063 | T21: 17601 | U21: 32462 | V21: 25.08 | W21: =C21 / R21 -> 25.078701 | X21: 56858 | Y21: =C21 / V21 -> 50060.407 | Z21: 1.14 | AA21: =ROUND(X21/R21, 2) -> 1.14 | AB21: 0.1944 | AC21: =ROUND(X21 / N21, 4) -> 0.1944 | AD21: 691439 | AE21: 564076 | AF21: 0.55072142 | AG21: =ROUND(AD21 / C21, 4) -> 0.5507 | AH21: 0.44927858 | AI21: =ROUND(AE21 / C21, 4) -> 0.4493
A22: 45689 | B22: Account | C22: 1140886 | D22: =AD22 + AE22 -> 1140886 | E22: 273131 | F22: 0.2394 | G22: =ROUND(E22/C22, 4) -> 0.2394 | H22: 0.1783 | I22: =ROUND(R22/N22, 4) -> 0.1783 | J22: 0.2875 | K22: =ROUND(T22/P22, 4) -> 0.2875 | L22: 0.1457 | M22: =ROUND(U22/Q22, 4) -> 0.1457 | N22: 256900 | O22: =P22 + Q22 -> 256900 | P22: 59041 | Q22: 197859 | R22: 45805 | S22: =T22 + U22 -> 45805 | T22: 16973 | U22: 28832 | V22: 24.91 | W22: =C22 / R22 -> 24.907456 | X22: 51979 | Y22: =C22 / V22 -> 45800.321 | Z22: 1.13 | AA22: =ROUND(X22/R22, 2) -> 1.13 | AB22: 0.2023 | AC22: =ROUND(X22 / N22, 4) -> 0.2023 | AD22: 599779 | AE22: 541107 | AF22: 0.52571335 | AG22: =ROUND(AD22 / C22, 4) -> 0.5257 | AH22: 0.47428665 | AI22: =ROUND(AE22 / C22, 4) -> 0.4743
A23: 45717 | B23: Account | C23: 1171220 | D23: =AD23 + AE23 -> 1171220 | E23: 327361 | F23: 0.2795 | G23: =ROUND(E23/C23, 4) -> 0.2795 | H23: 0.1824 | I23: =ROUND(R23/N23, 4) -> 0.1824 | J23: 0.3334 | K23: =ROUND(T23/P23, 4) -> 0.3334 | L23: 0.1641 | M23: =ROUND(U23/Q23, 4) -> 0.1641 | N23: 256817 | O23: =P23 + Q23 -> 256817 | P23: 27733 | Q23: 229084 | R23: 46843 | S23: =T23 + U23 -> 46843 | T23: 9247 | U23: 37596 | V23: 25 | W23: =C23 / R23 -> 25.003095 | X23: 53774 | Y23: =C23 / V23 -> 46848.8 | Z23: 1.15 | AA23: =ROUND(X23/R23, 2) -> 1.15 | AB23: 0.2094 | AC23: =ROUND(X23 / N23, 4) -> 0.2094 | AD23: 542519 | AE23: 628701 | AF23: 0.46320845 | AG23: =ROUND(AD23 / C23, 4) -> 0.4632 | AH23: 0.53679155 | AI23: =ROUND(AE23 / C23, 4) -> 0.5368
A24: 45748 | B24: Account | C24: 1148444 | D24: =AD24 + AE24 -> 1148444 | E24: 301006 | F24: 0.2621 | G24: =ROUND(E24/C24, 4) -> 0.2621 | H24: 0.1975 | I24: =ROUND(R24/N24, 4) -> 0.1975 | J24: 0.3044 | K24: =ROUND(T24/P24, 4) -> 0.3044 | L24: 0.1737 | M24: =ROUND(U24/Q24, 4) -> 0.1737 | N24: 227683 | O24: =P24 + Q24 -> 227683 | P24: 41437 | Q24: 186246 | R24: 44960 | S24: =T24 + U24 -> 44960 | T24: 12614 | U24: 32346 | V24: 25.54 | W24: =C24 / R24 -> 25.543683 | X24: 50663 | Y24: =C24 / V24 -> 44966.484 | Z24: 1.13 | AA24: =ROUND(X24/R24, 2) -> 1.13 | AB24: 0.2225 | AC24: =ROUND(X24 / N24, 4) -> 0.2225 | AD24: 529055 | AE24: 619389 | AF24: 0.46067113 | AG24: =ROUND(AD24 / C24, 4) -> 0.4607 | AH24: 0.53932887 | AI24: =ROUND(AE24 / C24, 4) -> 0.5393
A25: 45778 | B25: Account | C25: 1231499 | D25: =AD25 + AE25 -> 1231499 | E25: 322128 | F25: 0.2616 | G25: =ROUND(E25/C25, 4) -> 0.2616 | H25: 0.2054 | I25: =ROUND(R25/N25, 4) -> 0.2054 | J25: 0.3054 | K25: =ROUND(T25/P25, 4) -> 0.3054 | L25: 0.1788 | M25: =ROUND(U25/Q25, 4) -> 0.1788 | N25: 231747 | O25: =P25 + Q25 -> 231747 | P25: 48607 | Q25: 183140 | R25: 47596 | S25: =T25 + U25 -> 47596 | T25: 14846 | U25: 32750 | V25: 25.87 | W25: =C25 / R25 -> 25.874002 | X25: 53380 | Y25: =C25 / V25 -> 47603.363 | Z25: 1.12 | AA25: =ROUND(X25/R25, 2) -> 1.12 | AB25: 0.2303 | AC25: =ROUND(X25 / N25, 4) -> 0.2303 | AD25: 560738 | AE25: 670761 | AF25: 0.45532964 | AG25: =ROUND(AD25 / C25, 4) -> 0.4553 | AH25: 0.54467036 | AI25: =ROUND(AE25 / C25, 4) -> 0.5447
A26: 45809 | B26: Account | C26: 1153194 | D26: =AD26 + AE26 -> 1153194 | E26: 287063 | F26: 0.2489 | G26: =ROUND(E26/C26, 4) -> 0.2489 | H26: 0.2205 | I26: =ROUND(R26/N26, 4) -> 0.2205 | J26: 0.3013 | K26: =ROUND(T26/P26, 4) -> 0.3013 | L26: 0.1901 | M26: =ROUND(U26/Q26, 4) -> 0.1901 | N26: 199812 | O26: =P26 + Q26 -> 199812 | P26: 54623 | Q26: 145189 | R26: 44056 | S26: =T26 + U26 -> 44056 | T26: 16459 | U26: 27597 | V26: 26.18 | W26: =C26 / R26 -> 26.17564 | X26: 49160 | Y26: =C26 / V26 -> 44048.663 | Z26: 1.12 | AA26: =ROUND(X26/R26, 2) -> 1.12 | AB26: 0.246 | AC26: =ROUND(X26 / N26, 4) -> 0.246 | AD26: 504737 | AE26: 648457 | AF26: 0.43768611 | AG26: =ROUND(AD26 / C26, 4) -> 0.4377 | AH26: 0.56231389 | AI26: =ROUND(AE26 / C26, 4) -> 0.5623
A27: 45839 | B27: Account | C27: 1420531 | D27: =AD27 + AE27 -> 1420248 | E27: 334195 | F27: 0.2353 | G27: =ROUND(E27/C27, 4) -> 0.2353 | H27: 0.2336 | I27: =ROUND(R27/N27, 4) -> 0.2336 | J27: 0.3047 | K27: =ROUND(T27/P27, 4) -> 0.3047 | L27: 0.2186 | M27: =ROUND(U27/Q27, 4) -> 0.2186 | N27: 244791 | O27: =P27 + Q27 -> 244791 | P27: 42654 | Q27: 202137 | R27: 57185 | S27: =T27 + U27 -> 57185 | T27: 12996 | U27: 44189 | V27: 24.84 | W27: =C27 / R27 -> 24.840972 | X27: 66691 | Y27: =C27 / V27 -> 57187.238 | Z27: 1.17 | AA27: =ROUND(X27/R27, 2) -> 1.17 | AB27: 0.2724 | AC27: =ROUND(X27 / N27, 4) -> 0.2724 | AD27: 565181 | AE27: 855067 | AF27: 0.39794529 | AG27: =ROUND(AD27 / C27, 4) -> 0.3979 | AH27: 0.60205471 | AI27: =ROUND(AE27 / C27, 4) -> 0.6019
A28: 45870 | B28: Account | C28: 1359264 | D28: =AD28 + AE28 -> 1356219 | E28: 320874 | F28: 0.2361 | G28: =ROUND(E28/C28, 4) -> 0.2361 | H28: 0.2421 | I28: =ROUND(R28/N28, 4) -> 0.2421 | J28: 0.3303 | K28: =ROUND(T28/P28, 4) -> 0.3303 | L28: 0.2174 | M28: =ROUND(U28/Q28, 4) -> 0.2174 | N28: 228398 | O28: =P28 + Q28 -> 228398 | P28: 50012 | Q28: 178386 | R28: 55298 | S28: =T28 + U28 -> 55298 | T28: 16518 | U28: 38780 | V28: 24.58 | W28: =C28 / R28 -> 24.580708 | X28: 63365 | Y28: =C28 / V28 -> 55299.593 | Z28: 1.15 | AA28: =ROUND(X28/R28, 2) -> 1.15 | AB28: 0.2774 | AC28: =ROUND(X28 / N28, 4) -> 0.2774 | AD28: 623587 | AE28: 732632 | AF28: 0.45979816 | AG28: =ROUND(AD28 / C28, 4) -> 0.4588 | AH28: 0.54020184 | AI28: =ROUND(AE28 / C28, 4) -> 0.539
A29: 45505 | B29: Ashwagandha | C29: 157936 | D29: =AD29 + AE29 -> 157936 | E29: 34841 | F29: 0.2206 | G29: =ROUND(E29/C29, 4) -> 0.2206 | H29: 0.1951 | I29: =ROUND(R29/N29, 4) -> 0.1951 | J29: 0.3302 | K29: =ROUND(T29/P29, 4) -> 0.3302 | L29: 0.168 | M29: =ROUND(U29/Q29, 4) -> 0.168 | N29: 42573 | O29: =P29 + Q29 -> 42573 | P29: 7101 | Q29: 35472 | R29: 8304 | S29: =T29 + U29 -> 8304 | T29: 2345 | U29: 5959 | V29: =C29 / R29 -> 19.019268 | W29: =C29 / R29 -> 19.019268 | X29: =C29 / V29 -> 8304 | Y29: =C29 / V29 -> 8304 | Z29: =ROUND(X29/R29, 2) -> 1 | AA29: =ROUND(X29/R29, 2) -> 1 | AB29: =ROUND(X29 / N29, 4) -> 0.1951 | AC29: =ROUND(X29 / N29, 4) -> 0.1951 | AD29: 78543 | AE29: 79393 | AF29: 0.49730904 | AG29: =ROUND(AD29 / C29, 4) -> 0.4973 | AH29: 0.50269096 | AI29: =ROUND(AE29 / C29, 4) -> 0.5027
A30: 45536 | B30: Ashwagandha | C30: 153828 | D30: =AD30 + AE30 -> 153828 | E30: 30441 | F30: 0.1979 | G30: =ROUND(E30/C30, 4) -> 0.1979 | H30: 0.2091 | I30: =ROUND(R30/N30, 4) -> 0.2091 | J30: 0.3376 | K30: =ROUND(T30/P30, 4) -> 0.3376 | L30: 0.177 | M30: =ROUND(U30/Q30, 4) -> 0.177 | N30: 38401 | O30: =P30 + Q30 -> 38401 | P30: 7658 | Q30: 30743 | R30: 8028 | S30: =T30 + U30 -> 8028 | T30: 2585 | U30: 5443 | V30: =C30 / R30 -> 19.161435 | W30: =C30 / R30 -> 19.161435 | X30: =C30 / V30 -> 8028 | Y30: =C30 / V30 -> 8028 | Z30: =ROUND(X30/R30, 2) -> 1 | AA30: =ROUND(X30/R30, 2) -> 1 | AB30: =ROUND(X30 / N30, 4) -> 0.2091 | AC30: =ROUND(X30 / N30, 4) -> 0.2091 | AD30: 74109 | AE30: 79719 | AF30: 0.48176535 | AG30: =ROUND(AD30 / C30, 4) -> 0.4818 | AH30: 0.51823465 | AI30: =ROUND(AE30 / C30, 4) -> 0.5182
A31: 45566 | B31: Ashwagandha | C31: 162480 | D31: =AD31 + AE31 -> 162480 | E31: 28164 | F31: 0.1733 | G31: =ROUND(E31/C31, 4) -> 0.1733 | H31: 0.2192 | I31: =ROUND(R31/N31, 4) -> 0.2192 | J31: 0.3171 | K31: =ROUND(T31/P31, 4) -> 0.3171 | L31: 0.1938 | M31: =ROUND(U31/Q31, 4) -> 0.1938 | N31: 38675 | O31: =P31 + Q31 -> 38675 | P31: 7967 | Q31: 30708 | R31: 8478 | S31: =T31 + U31 -> 8478 | T31: 2526 | U31: 5952 | V31: =C31 / R31 -> 19.164897 | W31: =C31 / R31 -> 19.164897 | X31: =C31 / V31 -> 8478 | Y31: =C31 / V31 -> 8478 | Z31: =ROUND(X31/R31, 2) -> 1 | AA31: =ROUND(X31/R31, 2) -> 1 | AB31: =ROUND(X31 / N31, 4) -> 0.2192 | AC31: =ROUND(X31 / N31, 4) -> 0.2192 | AD31: 72430 | AE31: 90050 | AF31: 0.44577794 | AG31: =ROUND(AD31 / C31, 4) -> 0.4458 | AH31: 0.55422206 | AI31: =ROUND(AE31 / C31, 4) -> 0.5542
A32: 45597 | B32: Ashwagandha | C32: 158885 | D32: =AD32 + AE32 -> 158885 | E32: 26311 | F32: 0.1656 | G32: =ROUND(E32/C32, 4) -> 0.1656 | H32: 0.2185 | I32: =ROUND(R32/N32, 4) -> 0.2185 | J32: 0.3344 | K32: =ROUND(T32/P32, 4) -> 0.3344 | L32: 0.1978 | M32: =ROUND(U32/Q32, 4) -> 0.1978 | N32: 38659 | O32: =P32 + Q32 -> 38659 | P32: 5858 | Q32: 32801 | R32: 8448 | S32: =T32 + U32 -> 8448 | T32: 1959 | U32: 6489 | V32: =C32 / R32 -> 18.80741 | W32: =C32 / R32 -> 18.80741 | X32: =C32 / V32 -> 8448 | Y32: =C32 / V32 -> 8448 | Z32: =ROUND(X32/R32, 2) -> 1 | AA32: =ROUND(X32/R32, 2) -> 1 | AB32: =ROUND(X32 / N32, 4) -> 0.2185 | AC32: =ROUND(X32 / N32, 4) -> 0.2185 | AD32: 69552 | AE32: 89333 | AF32: 0.43775057 | AG32: =ROUND(AD32 / C32, 4) -> 0.4378 | AH32: 0.56224943 | AI32: =ROUND(AE32 / C32, 4) -> 0.5622
A33: 45627 | B33: Ashwagandha | C33: 144048 | D33: =AD33 + AE33 -> 144048 | E33: 29089 | F33: 0.2019 | G33: =ROUND(E33/C33, 4) -> 0.2019 | H33: 0.2006 | I33: =ROUND(R33/N33, 4) -> 0.2006 | J33: 0.3083 | K33: =ROUND(T33/P33, 4) -> 0.3083 | L33: 0.1644 | M33: =ROUND(U33/Q33, 4) -> 0.1644 | N33: 36413 | O33: =P33 + Q33 -> 36413 | P33: 9146 | Q33: 27267 | R33: 7303 | S33: =T33 + U33 -> 7303 | T33: 2820 | U33: 4483 | V33: =C33 / R33 -> 19.724497 | W33: =C33 / R33 -> 19.724497 | X33: =C33 / V33 -> 7303 | Y33: =C33 / V33 -> 7303 | Z33: =ROUND(X33/R33, 2) -> 1 | AA33: =ROUND(X33/R33, 2) -> 1 | AB33: =ROUND(X33 / N33, 4) -> 0.2006 | AC33: =ROUND(X33 / N33, 4) -> 0.2006 | AD33: 66936 | AE33: 77112 | AF33: 0.46467844 | AG33: =ROUND(AD33 / C33, 4) -> 0.4647 | AH33: 0.53532156 | AI33: =ROUND(AE33 / C33, 4) -> 0.5353
A34: 45658 | B34: Ashwagandha | C34: 200911 | D34: =AD34 + AE34 -> 200911 | E34: 38753 | F34: 0.1929 | G34: =ROUND(E34/C34, 4) -> 0.1929 | H34: 0.1902 | I34: =ROUND(R34/N34, 4) -> 0.1902 | J34: 0.282 | K34: =ROUND(T34/P34, 4) -> 0.282 | L34: 0.138 | M34: =ROUND(U34/Q34, 4) -> 0.138 | N34: 53198 | O34: =P34 + Q34 -> 53198 | P34: 19278 | Q34: 33920 | R34: 10117 | S34: =T34 + U34 -> 10117 | T34: 5437 | U34: 4680 | V34: =C34 / R34 -> 19.858753 | W34: =C34 / R34 -> 19.858753 | X34: =C34 / V34 -> 10117 | Y34: =C34 / V34 -> 10117 | Z34: =ROUND(X34/R34, 2) -> 1 | AA34: =ROUND(X34/R34, 2) -> 1 | AB34: =ROUND(X34 / N34, 4) -> 0.1902 | AC34: =ROUND(X34 / N34, 4) -> 0.1902 | AD34: 108909 | AE34: 92002 | AF34: 0.54207584 | AG34: =ROUND(AD34 / C34, 4) -> 0.5421 | AH34: 0.45792416 | AI34: =ROUND(AE34 / C34, 4) -> 0.4579
A35: 45689 | B35: Ashwagandha | C35: 171789 | D35: =AD35 + AE35 -> 171789 | E35: 33744 | F35: 0.1964 | G35: =ROUND(E35/C35, 4) -> 0.1964 | H35: 0.1946 | I35: =ROUND(R35/N35, 4) -> 0.1946 | J35: 0.2598 | K35: =ROUND(T35/P35, 4) -> 0.2598 | L35: 0.1513 | M35: =ROUND(U35/Q35, 4) -> 0.1513 | N35: 43584 | O35: =P35 + Q35 -> 43584 | P35: 17402 | Q35: 26182 | R35: 8482 | S35: =T35 + U35 -> 8482 | T35: 4521 | U35: 3961 | V35: =C35 / R35 -> 20.25336 | W35: =C35 / R35 -> 20.25336 | X35: =C35 / V35 -> 8482 | Y35: =C35 / V35 -> 8482 | Z35: =ROUND(X35/R35, 2) -> 1 | AA35: =ROUND(X35/R35, 2) -> 1 | AB35: =ROUND(X35 / N35, 4) -> 0.1946 | AC35: =ROUND(X35 / N35, 4) -> 0.1946 | AD35: 85980 | AE35: 85809 | AF35: 0.5004977 | AG35: =ROUND(AD35 / C35, 4) -> 0.5005 | AH35: 0.4995023 | AI35: =ROUND(AE35 / C35, 4) -> 0.4995
A36: 45717 | B36: Ashwagandha | C36: 160501 | D36: =AD36 + AE36 -> 160501 | E36: 50164 | F36: 0.3125 | G36: =ROUND(E36/C36, 4) -> 0.3125 | H36: 0.2142 | I36: =ROUND(R36/N36, 4) -> 0.2142 | J36: 0.3623 | K36: =ROUND(T36/P36, 4) -> 0.3623 | L36: 0.2037 | M36: =ROUND(U36/Q36, 4) -> 0.2037 | N36: 37922 | O36: =P36 + Q36 -> 37922 | P36: 2498 | Q36: 35424 | R36: 8121 | S36: =T36 + U36 -> 8121 | T36: 905 | U36: 7216 | V36: =C36 / R36 -> 19.763699 | W36: =C36 / R36 -> 19.763699 | X36: =C36 / V36 -> 8121 | Y36: =C36 / V36 -> 8121 | Z36: =ROUND(X36/R36, 2) -> 1 | AA36: =ROUND(X36/R36, 2) -> 1 | AB36: =ROUND(X36 / N36, 4) -> 0.2142 | AC36: =ROUND(X36 / N36, 4) -> 0.2142 | AD36: 63043 | AE36: 97458 | AF36: 0.39278883 | AG36: =ROUND(AD36 / C36, 4) -> 0.3928 | AH36: 0.60721117 | AI36: =ROUND(AE36 / C36, 4) -> 0.6072
A37: 45748 | B37: Ashwagandha | C37: 145519 | D37: =AD37 + AE37 -> 145519 | E37: 35234 | F37: 0.2421 | G37: =ROUND(E37/C37, 4) -> 0.2421 | H37: 0.223 | I37: =ROUND(R37/N37, 4) -> 0.223 | J37: 0.289 | K37: =ROUND(T37/P37, 4) -> 0.289 | L37: 0.1895 | M37: =ROUND(U37/Q37, 4) -> 0.1895 | N37: 32328 | O37: =P37 + Q37 -> 32328 | P37: 10864 | Q37: 21464 | R37: 7208 | S37: =T37 + U37 -> 7208 | T37: 3140 | U37: 4068 | V37: =C37 / R37 -> 20.188541 | W37: =C37 / R37 -> 20.188541 | X37: =C37 / V37 -> 7208 | Y37: =C37 / V37 -> 7208 | Z37: =ROUND(X37/R37, 2) -> 1 | AA37: =ROUND(X37/R37, 2) -> 1 | AB37: =ROUND(X37 / N37, 4) -> 0.223 | AC37: =ROUND(X37 / N37, 4) -> 0.223 | AD37: 56854 | AE37: 88665 | AF37: 0.39069812 | AG37: =ROUND(AD37 / C37, 4) -> 0.3907 | AH37: 0.60930188 | AI37: =ROUND(AE37 / C37, 4) -> 0.6093
A38: 45778 | B38: Ashwagandha | C38: 150656 | D38: =AD38 + AE38 -> 150656 | E38: 34523 | F38: 0.2292 | G38: =ROUND(E38/C38, 4) -> 0.2292 | H38: 0.2276 | I38: =ROUND(R38/N38, 4) -> 0.2276 | J38: 0.2887 | K38: =ROUND(T38/P38, 4) -> 0.2887 | L38: 0.1938 | M38: =ROUND(U38/Q38, 4) -> 0.1938 | N38: 33319 | O38: =P38 + Q38 -> 33319 | P38: 11842 | Q38: 21477 | R38: 7582 | S38: =T38 + U38 -> 7582 | T38: 3419 | U38: 4163 | V38: =C38 / R38 -> 19.870219 | W38: =C38 / R38 -> 19.870219 | X38: =C38 / V38 -> 7582 | Y38: =C38 / V38 -> 7582 | Z38: =ROUND(X38/R38, 2) -> 1 | AA38: =ROUND(X38/R38, 2) -> 1 | AB38: =ROUND(X38 / N38, 4) -> 0.2276 | AC38: =ROUND(X38 / N38, 4) -> 0.2276 | AD38: 59553 | AE38: 91103 | AF38: 0.39529126 | AG38: =ROUND(AD38 / C38, 4) -> 0.3953 | AH38: 0.60470874 | AI38: =ROUND(AE38 / C38, 4) -> 0.6047
A39: 45809 | B39: Ashwagandha | C39: 148763 | D39: =AD39 + AE39 -> 148763 | E39: 30594 | F39: 0.2057 | G39: =ROUND(E39/C39, 4) -> 0.2057 | H39: 0.2472 | I39: =ROUND(R39/N39, 4) -> 0.2472 | J39: 0.2921 | K39: =ROUND(T39/P39, 4) -> 0.2921 | L39: 0.2193 | M39: =ROUND(U39/Q39, 4) -> 0.2193 | N39: 30323 | O39: =P39 + Q39 -> 30323 | P39: 11623 | Q39: 18700 | R39: 7495 | S39: =T39 + U39 -> 7495 | T39: 3395 | U39: 4100 | V39: =C39 / R39 -> 19.848299 | W39: =C39 / R39 -> 19.848299 | X39: =C39 / V39 -> 7495 | Y39: =C39 / V39 -> 7495 | Z39: =ROUND(X39/R39, 2) -> 1 | AA39: =ROUND(X39/R39, 2) -> 1 | AB39: =ROUND(X39 / N39, 4) -> 0.2472 | AC39: =ROUND(X39 / N39, 4) -> 0.2472 | AD39: 59979 | AE39: 88784 | AF39: 0.40318493 | AG39: =ROUND(AD39 / C39, 4) -> 0.4032 | AH39: 0.59681507 | AI39: =ROUND(AE39 / C39, 4) -> 0.5968
A40: 45839 | B40: Ashwagandha | C40: 175649 | D40: =AD40 + AE40 -> 175649 | E40: 41857 | F40: 0.2383 | G40: =ROUND(E40/C40, 4) -> 0.2383 | H40: 0.2612 | I40: =ROUND(R40/N40, 4) -> 0.2612 | J40: 0.2921 | K40: =ROUND(T40/P40, 4) -> 0.2921 | L40: 0.2484 | M40: =ROUND(U40/Q40, 4) -> 0.2484 | N40: 34143 | O40: =P40 + Q40 -> 34143 | P40: 10013 | Q40: 24130 | R40: 8919 | S40: =T40 + U40 -> 8919 | T40: 2925 | U40: 5994 | V40: =C40 / R40 -> 19.6938 | W40: =C40 / R40 -> 19.6938 | X40: =C40 / V40 -> 8919 | Y40: =C40 / V40 -> 8919 | Z40: =ROUND(X40/R40, 2) -> 1 | AA40: =ROUND(X40/R40, 2) -> 1 | AB40: =ROUND(X40 / N40, 4) -> 0.2612 | AC40: =ROUND(X40 / N40, 4) -> 0.2612 | AD40: 65609 | AE40: 110040 | AF40: 0.37352333 | AG40: =ROUND(AD40 / C40, 4) -> 0.3735 | AH40: 0.62647667 | AI40: =ROUND(AE40 / C40, 4) -> 0.6265
... A54: 45870 | B54: K2D3 | C54: 115497 | D54: =AD54 + AE54 -> 115497 | E54: 23860 | F54: 0.2066 | G54: =ROUND(E54/C54, 4) -> 0.2066 | H54: 0.3748 | I54: =ROUND(R54/N54, 4) -> 0.3748 | J54: 0.3494 | K54: =ROUND(T54/P54, 4) -> 0.3494 | L54: 0.3896 | M54: =ROUND(U54/Q54, 4) -> 0.3896 | N54: 14604 | O54: =P54 + Q54 -> 14604 | P54: 5406 | Q54: 9198 | R54: 5473 | S54: =T54 + U54 -> 5473 | T54: 1889 | U54: 3584 | V54: =C54 / R54 -> 21.103051 | W54: =C54 / R54 -> 21.103051 | X54: =C54 / V54 -> 5473 | Y54: =C54 / V54 -> 5473 | Z54: =ROUND(X54/R54, 2) -> 1 | AA54: =ROUND(X54/R54, 2) -> 1 | AB54: =ROUND(X54 / N54, 4) -> 0.3748 | AC54: =ROUND(X54 / N54, 4) -> 0.3748 | AD54: 42524 | AE54: 72973 | AF54: 0.36818272 | AG54: =ROUND(AD54 / C54, 4) -> 0.3682 | AH54: 0.63181728 | AI54: =ROUND(AE54 / C54, 4) -> 0.6318

Sheet SQL_Bonus
A2: monthly_perf (month, entity, sales, profit, profit_margin, orders, sessions)
A4: Exercise 1: Show sales and profit by entity for the last 6 months
A6: SELECT SUM(sales), SUM(profit), entity FROM monthly_perf WHERE to_date(month, 'YYYY-MM') >= date_trunc('month', CURRENT_DATE) - INTERVAL '6 months' GROUP BY entity LIMIT 10;
